timeseer_client/__init__.py
timeseer_client/setup.py
timeseer_client/internal/__init__.py
timeseer_client/internal/client.py
timeseer_client/internal/data_services.py
timeseer_client/internal/data_sets.py
timeseer_client/internal/data_substitutions.py
timeseer_client/internal/data_uploader_pandas.py
timeseer_client/internal/filters.py
timeseer_client/internal/filters_arrow.py
timeseer_client/internal/filters_pandas.py
timeseer_client/internal/flows.py
timeseer_client/internal/profile.py
timeseer_client/internal/resources.py
timeseer_client/internal/sources.py
timeseer_client/metadata/__init__.py
timeseer_client/metadata/fields.py
timeseer-1.0.16.dist-info/METADATA
timeseer-1.0.16.dist-info/WHEEL
timeseer-1.0.16.dist-info/top_level.txt
timeseer-1.0.16.dist-info/RECORD
