Metadata-Version: 2.1
Name: timeseer
Version: 1.0.16
Summary: Python SDK for Timeseer.AI
Author-email: "Timeseer.AI" <pypi@timeseer.ai>
License: Copyright Timeseer.AI 2023
Project-URL: Homepage, https://timeseer.ai/
Classifier: Programming Language :: Python :: 3
Classifier: Operating System :: OS Independent
Requires-Python: >=3.8
Requires-Dist: kukur >=0.0.21
Requires-Dist: pyarrow
